pyearthviz3d/__init__.py
pyearthviz3d/geovista/__init__.py
pyearthviz3d/geovista/animate_polyline_file_on_sphere.py
pyearthviz3d/geovista/animate_rotating_frames.py
pyearthviz3d/geovista/animate_time_series_frames.py
pyearthviz3d/geovista/map_single_frame.py
pyearthviz3d/geovista/utility.py
pyearthviz3d-0.1.0.dist-info/licenses/LICENSE
pyearthviz3d-0.1.0.dist-info/METADATA
pyearthviz3d-0.1.0.dist-info/WHEEL
pyearthviz3d-0.1.0.dist-info/top_level.txt
pyearthviz3d-0.1.0.dist-info/RECORD
